uforgecli/__init__.py
uforgecli/uforgecli.py
uforgecli/commands/__init__.py
uforgecli/commands/entitlement/__init__.py
uforgecli/commands/entitlement/entitlement.py
uforgecli/commands/images/__init__.py
uforgecli/commands/images/images.py
uforgecli/commands/org/__init__.py
uforgecli/commands/org/org.py
uforgecli/commands/org/org_category.py
uforgecli/commands/org/org_format.py
uforgecli/commands/org/org_golden.py
uforgecli/commands/org/org_os.py
uforgecli/commands/org/org_repo.py
uforgecli/commands/org/org_repo_os.py
uforgecli/commands/org/org_repo_refresh.py
uforgecli/commands/org/org_targetFormat.py
uforgecli/commands/org/org_targetPlatform.py
uforgecli/commands/org/org_user.py
uforgecli/commands/os/__init__.py
uforgecli/commands/os/os.py
uforgecli/commands/os/os_milestone.py
uforgecli/commands/pimages/__init__.py
uforgecli/commands/pimages/pimages.py
uforgecli/commands/role/__init__.py
uforgecli/commands/role/role.py
uforgecli/commands/role/role_entitlement.py
uforgecli/commands/subscription/__init__.py
uforgecli/commands/subscription/subscription.py
uforgecli/commands/subscription/subscription_admin.py
uforgecli/commands/subscription/subscription_os.py
uforgecli/commands/subscription/subscription_quota.py
uforgecli/commands/subscription/subscription_role.py
uforgecli/commands/subscription/subscription_targetFormat.py
uforgecli/commands/subscription/subscription_targetPlatform.py
uforgecli/commands/template/__init__.py
uforgecli/commands/template/template.py
uforgecli/commands/template/template_info.py
uforgecli/commands/user/__init__.py
uforgecli/commands/user/user.py
uforgecli/commands/user/user_admin.py
uforgecli/commands/user/user_api.py
uforgecli/commands/user/user_org.py
uforgecli/commands/user/user_os.py
uforgecli/commands/user/user_quota.py
uforgecli/commands/user/user_role.py
uforgecli/commands/user/user_targetFormat.py
uforgecli/commands/user/user_targetPlatform.py
uforgecli/utils/__init__.py
uforgecli-3.8.13.dist-info/DESCRIPTION.rst
uforgecli-3.8.13.dist-info/METADATA
uforgecli-3.8.13.dist-info/RECORD
uforgecli-3.8.13.dist-info/WHEEL
uforgecli-3.8.13.dist-info/metadata.json
uforgecli-3.8.13.dist-info/top_level.txt
