Metadata-Version: 2.0
Name: uforgecli
Version: 3.8.13
Summary: UNKNOWN
Home-page: UNKNOWN
Author: UShareSoft
Author-email: contact@usharesoft.com
License: Apache License 2.0
Platform: UNKNOWN
Classifier: Development Status :: 4 - Beta
Classifier: Environment :: Console
Classifier: Intended Audience :: Developers
Classifier: Intended Audience :: System Administrators
Classifier: Natural Language :: English
Classifier: Operating System :: MacOS :: MacOS X
Classifier: Operating System :: Microsoft :: Windows
Classifier: Operating System :: POSIX
Classifier: License :: OSI Approved :: Apache Software License
Classifier: Programming Language :: Python
Classifier: Programming Language :: Python :: 2.6
Classifier: Programming Language :: Python :: 2.7
Requires-Dist: uforge-python-sdk (==3.8.13)
Requires-Dist: httplib2 (==0.9)
Requires-Dist: cmd2 (==0.6.7)
Requires-Dist: texttable (>=0.8.1)
Requires-Dist: progressbar (==2.3)
Requires-Dist: argparse
Requires-Dist: pyparsing (==2.0.2)
Requires-Dist: hurry.filesize (==0.9)
Requires-Dist: termcolor (==1.1.0)
Requires-Dist: xmlrunner (==1.7.7)
Requires-Dist: ussclicore (==1.0.11)
